{
  "indexes": [
    {
      "collectionGroup": "leaveRequests",
      "queryScope": "COLLECTION",
      "fields": [
        { "fieldPath": "studentUid", "order": "ASCENDING" },
        { "fieldPath": "requestedAt", "order": "ASCENDING" }
      ]
    },
    {
      "collectionGroup": "leaveRequests",
      "queryScope": "COLLECTION",
      "fields": [
        { "fieldPath": "studentUid", "order": "ASCENDING" },
        { "fieldPath": "requestedAt", "order": "DESCENDING" }
      ]
    },
    {
      "collectionGroup": "accessEvents",
      "queryScope": "COLLECTION",
      "fields": [
        { "fieldPath": "userId", "order": "ASCENDING" },
        { "fieldPath": "timestamp", "order": "ASCENDING" }
      ]
    },
    {
      "collectionGroup": "accessEvents",
      "queryScope": "COLLECTION",
      "fields": [
        { "fieldPath": "userId", "order": "ASCENDING" },
        { "fieldPath": "timestamp", "order": "DESCENDING" }
      ]
    },
    {
      "collectionGroup": "leaveRequests",
      "queryScope": "COLLECTION",
      "fields": [
        { "fieldPath": "classId", "order": "ASCENDING" },
        { "fieldPath": "status", "order": "ASCENDING" },
        { "fieldPath": "requestedAt", "order": "DESCENDING" }
      ]
    },
    {
      "collectionGroup": "leaveRequests",
      "queryScope": "COLLECTION",
      "fields": [
        { "fieldPath": "classId", "order": "ASCENDING" },
        { "fieldPath": "requestedAt", "order": "DESCENDING" }
      ]
    },
    {
      "collectionGroup": "users",
      "queryScope": "COLLECTION",
      "fields": [
        { "fieldPath": "classId", "order": "ASCENDING" },
        { "fieldPath": "role", "order": "ASCENDING" },
        { "fieldPath": "fullName", "order": "ASCENDING" }
      ]
    },
    {
      "collectionGroup": "accessEvents",
      "queryScope": "COLLECTION",
      "fields": [
        { "fieldPath": "classId", "order": "ASCENDING" },
        { "fieldPath": "timestamp", "order": "DESCENDING" }
      ]
    },
    {
      "collectionGroup": "volunteerOpportunities",
      "queryScope": "COLLECTION",
      "fields": [
        { "fieldPath": "status", "order": "ASCENDING" },
        { "fieldPath": "date", "order": "DESCENDING" }
      ]
    },
    {
      "collectionGroup": "volunteerOpportunities",
      "queryScope": "COLLECTION",
      "fields": [
        { "fieldPath": "classId", "order": "ASCENDING" },
        { "fieldPath": "status", "order": "ASCENDING" },
        { "fieldPath": "date", "order": "DESCENDING" }
      ]
    },
    {
      "collectionGroup": "volunteerSignups",
      "queryScope": "COLLECTION",
      "fields": [
        { "fieldPath": "studentUid", "order": "ASCENDING" },
        { "fieldPath": "signedUpAt", "order": "DESCENDING" }
      ]
    },
    {
      "collectionGroup": "volunteerSignups",
      "queryScope": "COLLECTION",
      "fields": [
        { "fieldPath": "opportunityId", "order": "ASCENDING" },
        { "fieldPath": "signedUpAt", "order": "ASCENDING" }
      ]
    },
    {
      "collectionGroup": "volunteerSignups",
      "queryScope": "COLLECTION",
      "fields": [
        { "fieldPath": "classId", "order": "ASCENDING" },
        { "fieldPath": "status", "order": "ASCENDING" },
        { "fieldPath": "signedUpAt", "order": "DESCENDING" }
      ]
    },
    {
      "collectionGroup": "volunteerSignups",
      "queryScope": "COLLECTION",
      "fields": [
        { "fieldPath": "studentUid", "order": "ASCENDING" },
        { "fieldPath": "status", "order": "ASCENDING" }
      ]
    }
  ],
  "fieldOverrides": []
}
